{
    "task1": {
        "input": {},
        "name": "Chart Classification",
        "output": {
            "chart_type": "line"
        }
    },
    "task2": {
        "input": {
            "task1_output": {
                "chart_type": "line"
            }
        },
        "name": "Text Detection and Recognition",
        "output": {
            "text_blocks": [
                {
                    "id": 0,
                    "polygon": {
                        "x0": 470,
                        "x1": 496,
                        "x2": 496,
                        "x3": 470,
                        "y0": 682,
                        "y1": 682,
                        "y2": 698,
                        "y3": 698
                    },
                    "text": "0.6"
                },
                {
                    "id": 1,
                    "polygon": {
                        "x0": 601,
                        "x1": 627,
                        "x2": 627,
                        "x3": 601,
                        "y0": 682,
                        "y1": 682,
                        "y2": 698,
                        "y3": 698
                    },
                    "text": "0.8"
                },
                {
                    "id": 2,
                    "polygon": {
                        "x0": 731,
                        "x1": 757,
                        "x2": 757,
                        "x3": 731,
                        "y0": 683,
                        "y1": 683,
                        "y2": 699,
                        "y3": 699
                    },
                    "text": "1.0"
                },
                {
                    "id": 3,
                    "polygon": {
                        "x0": 338,
                        "x1": 364,
                        "x2": 364,
                        "x3": 338,
                        "y0": 682,
                        "y1": 682,
                        "y2": 698,
                        "y3": 698
                    },
                    "text": "0.4"
                },
                {
                    "id": 4,
                    "polygon": {
                        "x0": 205,
                        "x1": 231,
                        "x2": 231,
                        "x3": 205,
                        "y0": 683,
                        "y1": 683,
                        "y2": 699,
                        "y3": 699
                    },
                    "text": "0.2"
                },
                {
                    "id": 5,
                    "polygon": {
                        "x0": 73,
                        "x1": 99,
                        "x2": 99,
                        "x3": 73,
                        "y0": 683,
                        "y1": 683,
                        "y2": 699,
                        "y3": 699
                    },
                    "text": "0.0"
                },
                {
                    "id": 6,
                    "polygon": {
                        "x0": 53,
                        "x1": 79,
                        "x2": 79,
                        "x3": 53,
                        "y0": 662,
                        "y1": 662,
                        "y2": 678,
                        "y3": 678
                    },
                    "text": "0.0"
                },
                {
                    "id": 7,
                    "polygon": {
                        "x0": 53,
                        "x1": 79,
                        "x2": 79,
                        "x3": 53,
                        "y0": 533,
                        "y1": 533,
                        "y2": 549,
                        "y3": 549
                    },
                    "text": "0.2"
                },
                {
                    "id": 8,
                    "polygon": {
                        "x0": 54,
                        "x1": 80,
                        "x2": 80,
                        "x3": 54,
                        "y0": 401,
                        "y1": 401,
                        "y2": 417,
                        "y3": 417
                    },
                    "text": "0.4"
                },
                {
                    "id": 9,
                    "polygon": {
                        "x0": 51,
                        "x1": 77,
                        "x2": 77,
                        "x3": 51,
                        "y0": 270,
                        "y1": 270,
                        "y2": 286,
                        "y3": 286
                    },
                    "text": "0.6"
                },
                {
                    "id": 10,
                    "polygon": {
                        "x0": 53,
                        "x1": 79,
                        "x2": 79,
                        "x3": 53,
                        "y0": 138,
                        "y1": 138,
                        "y2": 154,
                        "y3": 154
                    },
                    "text": "0.8"
                },
                {
                    "id": 11,
                    "polygon": {
                        "x0": 52,
                        "x1": 78,
                        "x2": 78,
                        "x3": 52,
                        "y0": 7,
                        "y1": 7,
                        "y2": 23,
                        "y3": 23
                    },
                    "text": "1.0"
                },
                {
                    "id": 12,
                    "polygon": {
                        "x0": 5,
                        "x1": 32,
                        "x2": 32,
                        "x3": 5,
                        "y0": 273,
                        "y1": 273,
                        "y2": 402,
                        "y3": 402
                    },
                    "text": "Sensitivity"
                },
                {
                    "id": 13,
                    "polygon": {
                        "x0": 397,
                        "x1": 549,
                        "x2": 549,
                        "x3": 397,
                        "y0": 729,
                        "y1": 729,
                        "y2": 755,
                        "y3": 755
                    },
                    "text": "1-Specificity"
                },
                {
                    "id": 14,
                    "polygon": {
                        "x0": 533,
                        "x1": 621,
                        "x2": 621,
                        "x3": 533,
                        "y0": 406,
                        "y1": 406,
                        "y2": 422,
                        "y3": 422
                    },
                    "text": "AUC=0.841"
                }
            ]
        }
    },
    "task3": {
        "input": {
            "task1_output": {
                "chart_type": "line"
            },
            "task2_output": {
                "text_blocks": [
                    {
                        "id": 0,
                        "polygon": {
                            "x0": 470,
                            "x1": 496,
                            "x2": 496,
                            "x3": 470,
                            "y0": 682,
                            "y1": 682,
                            "y2": 698,
                            "y3": 698
                        },
                        "text": "0.6"
                    },
                    {
                        "id": 1,
                        "polygon": {
                            "x0": 601,
                            "x1": 627,
                            "x2": 627,
                            "x3": 601,
                            "y0": 682,
                            "y1": 682,
                            "y2": 698,
                            "y3": 698
                        },
                        "text": "0.8"
                    },
                    {
                        "id": 2,
                        "polygon": {
                            "x0": 731,
                            "x1": 757,
                            "x2": 757,
                            "x3": 731,
                            "y0": 683,
                            "y1": 683,
                            "y2": 699,
                            "y3": 699
                        },
                        "text": "1.0"
                    },
                    {
                        "id": 3,
                        "polygon": {
                            "x0": 338,
                            "x1": 364,
                            "x2": 364,
                            "x3": 338,
                            "y0": 682,
                            "y1": 682,
                            "y2": 698,
                            "y3": 698
                        },
                        "text": "0.4"
                    },
                    {
                        "id": 4,
                        "polygon": {
                            "x0": 205,
                            "x1": 231,
                            "x2": 231,
                            "x3": 205,
                            "y0": 683,
                            "y1": 683,
                            "y2": 699,
                            "y3": 699
                        },
                        "text": "0.2"
                    },
                    {
                        "id": 5,
                        "polygon": {
                            "x0": 73,
                            "x1": 99,
                            "x2": 99,
                            "x3": 73,
                            "y0": 683,
                            "y1": 683,
                            "y2": 699,
                            "y3": 699
                        },
                        "text": "0.0"
                    },
                    {
                        "id": 6,
                        "polygon": {
                            "x0": 53,
                            "x1": 79,
                            "x2": 79,
                            "x3": 53,
                            "y0": 662,
                            "y1": 662,
                            "y2": 678,
                            "y3": 678
                        },
                        "text": "0.0"
                    },
                    {
                        "id": 7,
                        "polygon": {
                            "x0": 53,
                            "x1": 79,
                            "x2": 79,
                            "x3": 53,
                            "y0": 533,
                            "y1": 533,
                            "y2": 549,
                            "y3": 549
                        },
                        "text": "0.2"
                    },
                    {
                        "id": 8,
                        "polygon": {
                            "x0": 54,
                            "x1": 80,
                            "x2": 80,
                            "x3": 54,
                            "y0": 401,
                            "y1": 401,
                            "y2": 417,
                            "y3": 417
                        },
                        "text": "0.4"
                    },
                    {
                        "id": 9,
                        "polygon": {
                            "x0": 51,
                            "x1": 77,
                            "x2": 77,
                            "x3": 51,
                            "y0": 270,
                            "y1": 270,
                            "y2": 286,
                            "y3": 286
                        },
                        "text": "0.6"
                    },
                    {
                        "id": 10,
                        "polygon": {
                            "x0": 53,
                            "x1": 79,
                            "x2": 79,
                            "x3": 53,
                            "y0": 138,
                            "y1": 138,
                            "y2": 154,
                            "y3": 154
                        },
                        "text": "0.8"
                    },
                    {
                        "id": 11,
                        "polygon": {
                            "x0": 52,
                            "x1": 78,
                            "x2": 78,
                            "x3": 52,
                            "y0": 7,
                            "y1": 7,
                            "y2": 23,
                            "y3": 23
                        },
                        "text": "1.0"
                    },
                    {
                        "id": 12,
                        "polygon": {
                            "x0": 5,
                            "x1": 32,
                            "x2": 32,
                            "x3": 5,
                            "y0": 273,
                            "y1": 273,
                            "y2": 402,
                            "y3": 402
                        },
                        "text": "Sensitivity"
                    },
                    {
                        "id": 13,
                        "polygon": {
                            "x0": 397,
                            "x1": 549,
                            "x2": 549,
                            "x3": 397,
                            "y0": 729,
                            "y1": 729,
                            "y2": 755,
                            "y3": 755
                        },
                        "text": "1-Specificity"
                    },
                    {
                        "id": 14,
                        "polygon": {
                            "x0": 533,
                            "x1": 621,
                            "x2": 621,
                            "x3": 533,
                            "y0": 406,
                            "y1": 406,
                            "y2": 422,
                            "y3": 422
                        },
                        "text": "AUC=0.841"
                    }
                ]
            }
        },
        "name": "Text Role Classification",
        "output": {
            "text_roles": [
                {
                    "id": 0,
                    "role": "tick_label"
                },
                {
                    "id": 1,
                    "role": "tick_label"
                },
                {
                    "id": 2,
                    "role": "tick_label"
                },
                {
                    "id": 3,
                    "role": "tick_label"
                },
                {
                    "id": 4,
                    "role": "tick_label"
                },
                {
                    "id": 5,
                    "role": "tick_label"
                },
                {
                    "id": 6,
                    "role": "tick_label"
                },
                {
                    "id": 7,
                    "role": "tick_label"
                },
                {
                    "id": 8,
                    "role": "tick_label"
                },
                {
                    "id": 9,
                    "role": "tick_label"
                },
                {
                    "id": 10,
                    "role": "tick_label"
                },
                {
                    "id": 11,
                    "role": "tick_label"
                },
                {
                    "id": 12,
                    "role": "axis_title"
                },
                {
                    "id": 13,
                    "role": "axis_title"
                },
                {
                    "id": 14,
                    "role": "other"
                }
            ]
        }
    },
    "task4": {
        "input": {
            "task1_output": {
                "chart_type": "line"
            },
            "task2_output": {
                "text_blocks": [
                    {
                        "id": 0,
                        "polygon": {
                            "x0": 470,
                            "x1": 496,
                            "x2": 496,
                            "x3": 470,
                            "y0": 682,
                            "y1": 682,
                            "y2": 698,
                            "y3": 698
                        },
                        "text": "0.6"
                    },
                    {
                        "id": 1,
                        "polygon": {
                            "x0": 601,
                            "x1": 627,
                            "x2": 627,
                            "x3": 601,
                            "y0": 682,
                            "y1": 682,
                            "y2": 698,
                            "y3": 698
                        },
                        "text": "0.8"
                    },
                    {
                        "id": 2,
                        "polygon": {
                            "x0": 731,
                            "x1": 757,
                            "x2": 757,
                            "x3": 731,
                            "y0": 683,
                            "y1": 683,
                            "y2": 699,
                            "y3": 699
                        },
                        "text": "1.0"
                    },
                    {
                        "id": 3,
                        "polygon": {
                            "x0": 338,
                            "x1": 364,
                            "x2": 364,
                            "x3": 338,
                            "y0": 682,
                            "y1": 682,
                            "y2": 698,
                            "y3": 698
                        },
                        "text": "0.4"
                    },
                    {
                        "id": 4,
                        "polygon": {
                            "x0": 205,
                            "x1": 231,
                            "x2": 231,
                            "x3": 205,
                            "y0": 683,
                            "y1": 683,
                            "y2": 699,
                            "y3": 699
                        },
                        "text": "0.2"
                    },
                    {
                        "id": 5,
                        "polygon": {
                            "x0": 73,
                            "x1": 99,
                            "x2": 99,
                            "x3": 73,
                            "y0": 683,
                            "y1": 683,
                            "y2": 699,
                            "y3": 699
                        },
                        "text": "0.0"
                    },
                    {
                        "id": 6,
                        "polygon": {
                            "x0": 53,
                            "x1": 79,
                            "x2": 79,
                            "x3": 53,
                            "y0": 662,
                            "y1": 662,
                            "y2": 678,
                            "y3": 678
                        },
                        "text": "0.0"
                    },
                    {
                        "id": 7,
                        "polygon": {
                            "x0": 53,
                            "x1": 79,
                            "x2": 79,
                            "x3": 53,
                            "y0": 533,
                            "y1": 533,
                            "y2": 549,
                            "y3": 549
                        },
                        "text": "0.2"
                    },
                    {
                        "id": 8,
                        "polygon": {
                            "x0": 54,
                            "x1": 80,
                            "x2": 80,
                            "x3": 54,
                            "y0": 401,
                            "y1": 401,
                            "y2": 417,
                            "y3": 417
                        },
                        "text": "0.4"
                    },
                    {
                        "id": 9,
                        "polygon": {
                            "x0": 51,
                            "x1": 77,
                            "x2": 77,
                            "x3": 51,
                            "y0": 270,
                            "y1": 270,
                            "y2": 286,
                            "y3": 286
                        },
                        "text": "0.6"
                    },
                    {
                        "id": 10,
                        "polygon": {
                            "x0": 53,
                            "x1": 79,
                            "x2": 79,
                            "x3": 53,
                            "y0": 138,
                            "y1": 138,
                            "y2": 154,
                            "y3": 154
                        },
                        "text": "0.8"
                    },
                    {
                        "id": 11,
                        "polygon": {
                            "x0": 52,
                            "x1": 78,
                            "x2": 78,
                            "x3": 52,
                            "y0": 7,
                            "y1": 7,
                            "y2": 23,
                            "y3": 23
                        },
                        "text": "1.0"
                    },
                    {
                        "id": 12,
                        "polygon": {
                            "x0": 5,
                            "x1": 32,
                            "x2": 32,
                            "x3": 5,
                            "y0": 273,
                            "y1": 273,
                            "y2": 402,
                            "y3": 402
                        },
                        "text": "Sensitivity"
                    },
                    {
                        "id": 13,
                        "polygon": {
                            "x0": 397,
                            "x1": 549,
                            "x2": 549,
                            "x3": 397,
                            "y0": 729,
                            "y1": 729,
                            "y2": 755,
                            "y3": 755
                        },
                        "text": "1-Specificity"
                    },
                    {
                        "id": 14,
                        "polygon": {
                            "x0": 533,
                            "x1": 621,
                            "x2": 621,
                            "x3": 533,
                            "y0": 406,
                            "y1": 406,
                            "y2": 422,
                            "y3": 422
                        },
                        "text": "AUC=0.841"
                    }
                ]
            }
        },
        "name": "Axes Analysis",
        "output": {
            "_plot_bb": {
                "height": 658,
                "width": 659,
                "x0": 87,
                "y0": 10
            },
            "axes": {
                "_x-tick-type": "markers",
                "_x2-tick-type": null,
                "_y-tick-type": "markers",
                "_y2-tick-type": null,
                "x-axis": [
                    {
                        "id": 5,
                        "tick_pt": {
                            "x": 87,
                            "y": 668
                        }
                    },
                    {
                        "id": 4,
                        "tick_pt": {
                            "x": 219,
                            "y": 668
                        }
                    },
                    {
                        "id": 3,
                        "tick_pt": {
                            "x": 351,
                            "y": 668
                        }
                    },
                    {
                        "id": 0,
                        "tick_pt": {
                            "x": 482,
                            "y": 668
                        }
                    },
                    {
                        "id": 1,
                        "tick_pt": {
                            "x": 614,
                            "y": 668
                        }
                    },
                    {
                        "id": 2,
                        "tick_pt": {
                            "x": 746,
                            "y": 668
                        }
                    }
                ],
                "x-axis-2": [],
                "y-axis": [
                    {
                        "id": 11,
                        "tick_pt": {
                            "x": 87,
                            "y": 10
                        }
                    },
                    {
                        "id": 10,
                        "tick_pt": {
                            "x": 87,
                            "y": 142
                        }
                    },
                    {
                        "id": 9,
                        "tick_pt": {
                            "x": 87,
                            "y": 273
                        }
                    },
                    {
                        "id": 8,
                        "tick_pt": {
                            "x": 87,
                            "y": 405
                        }
                    },
                    {
                        "id": 7,
                        "tick_pt": {
                            "x": 87,
                            "y": 537
                        }
                    },
                    {
                        "id": 6,
                        "tick_pt": {
                            "x": 87,
                            "y": 668
                        }
                    }
                ],
                "y-axis-2": []
            }
        }
    },
    "task5": {
        "input": {
            "task1_output": {
                "chart_type": "line"
            },
            "task2_output": {
                "text_blocks": [
                    {
                        "id": 0,
                        "polygon": {
                            "x0": 470,
                            "x1": 496,
                            "x2": 496,
                            "x3": 470,
                            "y0": 682,
                            "y1": 682,
                            "y2": 698,
                            "y3": 698
                        },
                        "text": "0.6"
                    },
                    {
                        "id": 1,
                        "polygon": {
                            "x0": 601,
                            "x1": 627,
                            "x2": 627,
                            "x3": 601,
                            "y0": 682,
                            "y1": 682,
                            "y2": 698,
                            "y3": 698
                        },
                        "text": "0.8"
                    },
                    {
                        "id": 2,
                        "polygon": {
                            "x0": 731,
                            "x1": 757,
                            "x2": 757,
                            "x3": 731,
                            "y0": 683,
                            "y1": 683,
                            "y2": 699,
                            "y3": 699
                        },
                        "text": "1.0"
                    },
                    {
                        "id": 3,
                        "polygon": {
                            "x0": 338,
                            "x1": 364,
                            "x2": 364,
                            "x3": 338,
                            "y0": 682,
                            "y1": 682,
                            "y2": 698,
                            "y3": 698
                        },
                        "text": "0.4"
                    },
                    {
                        "id": 4,
                        "polygon": {
                            "x0": 205,
                            "x1": 231,
                            "x2": 231,
                            "x3": 205,
                            "y0": 683,
                            "y1": 683,
                            "y2": 699,
                            "y3": 699
                        },
                        "text": "0.2"
                    },
                    {
                        "id": 5,
                        "polygon": {
                            "x0": 73,
                            "x1": 99,
                            "x2": 99,
                            "x3": 73,
                            "y0": 683,
                            "y1": 683,
                            "y2": 699,
                            "y3": 699
                        },
                        "text": "0.0"
                    },
                    {
                        "id": 6,
                        "polygon": {
                            "x0": 53,
                            "x1": 79,
                            "x2": 79,
                            "x3": 53,
                            "y0": 662,
                            "y1": 662,
                            "y2": 678,
                            "y3": 678
                        },
                        "text": "0.0"
                    },
                    {
                        "id": 7,
                        "polygon": {
                            "x0": 53,
                            "x1": 79,
                            "x2": 79,
                            "x3": 53,
                            "y0": 533,
                            "y1": 533,
                            "y2": 549,
                            "y3": 549
                        },
                        "text": "0.2"
                    },
                    {
                        "id": 8,
                        "polygon": {
                            "x0": 54,
                            "x1": 80,
                            "x2": 80,
                            "x3": 54,
                            "y0": 401,
                            "y1": 401,
                            "y2": 417,
                            "y3": 417
                        },
                        "text": "0.4"
                    },
                    {
                        "id": 9,
                        "polygon": {
                            "x0": 51,
                            "x1": 77,
                            "x2": 77,
                            "x3": 51,
                            "y0": 270,
                            "y1": 270,
                            "y2": 286,
                            "y3": 286
                        },
                        "text": "0.6"
                    },
                    {
                        "id": 10,
                        "polygon": {
                            "x0": 53,
                            "x1": 79,
                            "x2": 79,
                            "x3": 53,
                            "y0": 138,
                            "y1": 138,
                            "y2": 154,
                            "y3": 154
                        },
                        "text": "0.8"
                    },
                    {
                        "id": 11,
                        "polygon": {
                            "x0": 52,
                            "x1": 78,
                            "x2": 78,
                            "x3": 52,
                            "y0": 7,
                            "y1": 7,
                            "y2": 23,
                            "y3": 23
                        },
                        "text": "1.0"
                    },
                    {
                        "id": 12,
                        "polygon": {
                            "x0": 5,
                            "x1": 32,
                            "x2": 32,
                            "x3": 5,
                            "y0": 273,
                            "y1": 273,
                            "y2": 402,
                            "y3": 402
                        },
                        "text": "Sensitivity"
                    },
                    {
                        "id": 13,
                        "polygon": {
                            "x0": 397,
                            "x1": 549,
                            "x2": 549,
                            "x3": 397,
                            "y0": 729,
                            "y1": 729,
                            "y2": 755,
                            "y3": 755
                        },
                        "text": "1-Specificity"
                    },
                    {
                        "id": 14,
                        "polygon": {
                            "x0": 533,
                            "x1": 621,
                            "x2": 621,
                            "x3": 533,
                            "y0": 406,
                            "y1": 406,
                            "y2": 422,
                            "y3": 422
                        },
                        "text": "AUC=0.841"
                    }
                ]
            }
        },
        "name": "Legend Analysis",
        "output": {
            "legend_pairs": []
        }
    },
    "task6": {
        "input": {
            "task1_output": {
                "chart_type": "line"
            },
            "task2_output": {
                "text_blocks": [
                    {
                        "id": 0,
                        "polygon": {
                            "x0": 470,
                            "x1": 496,
                            "x2": 496,
                            "x3": 470,
                            "y0": 682,
                            "y1": 682,
                            "y2": 698,
                            "y3": 698
                        },
                        "text": "0.6"
                    },
                    {
                        "id": 1,
                        "polygon": {
                            "x0": 601,
                            "x1": 627,
                            "x2": 627,
                            "x3": 601,
                            "y0": 682,
                            "y1": 682,
                            "y2": 698,
                            "y3": 698
                        },
                        "text": "0.8"
                    },
                    {
                        "id": 2,
                        "polygon": {
                            "x0": 731,
                            "x1": 757,
                            "x2": 757,
                            "x3": 731,
                            "y0": 683,
                            "y1": 683,
                            "y2": 699,
                            "y3": 699
                        },
                        "text": "1.0"
                    },
                    {
                        "id": 3,
                        "polygon": {
                            "x0": 338,
                            "x1": 364,
                            "x2": 364,
                            "x3": 338,
                            "y0": 682,
                            "y1": 682,
                            "y2": 698,
                            "y3": 698
                        },
                        "text": "0.4"
                    },
                    {
                        "id": 4,
                        "polygon": {
                            "x0": 205,
                            "x1": 231,
                            "x2": 231,
                            "x3": 205,
                            "y0": 683,
                            "y1": 683,
                            "y2": 699,
                            "y3": 699
                        },
                        "text": "0.2"
                    },
                    {
                        "id": 5,
                        "polygon": {
                            "x0": 73,
                            "x1": 99,
                            "x2": 99,
                            "x3": 73,
                            "y0": 683,
                            "y1": 683,
                            "y2": 699,
                            "y3": 699
                        },
                        "text": "0.0"
                    },
                    {
                        "id": 6,
                        "polygon": {
                            "x0": 53,
                            "x1": 79,
                            "x2": 79,
                            "x3": 53,
                            "y0": 662,
                            "y1": 662,
                            "y2": 678,
                            "y3": 678
                        },
                        "text": "0.0"
                    },
                    {
                        "id": 7,
                        "polygon": {
                            "x0": 53,
                            "x1": 79,
                            "x2": 79,
                            "x3": 53,
                            "y0": 533,
                            "y1": 533,
                            "y2": 549,
                            "y3": 549
                        },
                        "text": "0.2"
                    },
                    {
                        "id": 8,
                        "polygon": {
                            "x0": 54,
                            "x1": 80,
                            "x2": 80,
                            "x3": 54,
                            "y0": 401,
                            "y1": 401,
                            "y2": 417,
                            "y3": 417
                        },
                        "text": "0.4"
                    },
                    {
                        "id": 9,
                        "polygon": {
                            "x0": 51,
                            "x1": 77,
                            "x2": 77,
                            "x3": 51,
                            "y0": 270,
                            "y1": 270,
                            "y2": 286,
                            "y3": 286
                        },
                        "text": "0.6"
                    },
                    {
                        "id": 10,
                        "polygon": {
                            "x0": 53,
                            "x1": 79,
                            "x2": 79,
                            "x3": 53,
                            "y0": 138,
                            "y1": 138,
                            "y2": 154,
                            "y3": 154
                        },
                        "text": "0.8"
                    },
                    {
                        "id": 11,
                        "polygon": {
                            "x0": 52,
                            "x1": 78,
                            "x2": 78,
                            "x3": 52,
                            "y0": 7,
                            "y1": 7,
                            "y2": 23,
                            "y3": 23
                        },
                        "text": "1.0"
                    },
                    {
                        "id": 12,
                        "polygon": {
                            "x0": 5,
                            "x1": 32,
                            "x2": 32,
                            "x3": 5,
                            "y0": 273,
                            "y1": 273,
                            "y2": 402,
                            "y3": 402
                        },
                        "text": "Sensitivity"
                    },
                    {
                        "id": 13,
                        "polygon": {
                            "x0": 397,
                            "x1": 549,
                            "x2": 549,
                            "x3": 397,
                            "y0": 729,
                            "y1": 729,
                            "y2": 755,
                            "y3": 755
                        },
                        "text": "1-Specificity"
                    },
                    {
                        "id": 14,
                        "polygon": {
                            "x0": 533,
                            "x1": 621,
                            "x2": 621,
                            "x3": 533,
                            "y0": 406,
                            "y1": 406,
                            "y2": 422,
                            "y3": 422
                        },
                        "text": "AUC=0.841"
                    }
                ]
            },
            "task3_output": {
                "text_roles": [
                    {
                        "id": 0,
                        "role": "tick_label"
                    },
                    {
                        "id": 1,
                        "role": "tick_label"
                    },
                    {
                        "id": 2,
                        "role": "tick_label"
                    },
                    {
                        "id": 3,
                        "role": "tick_label"
                    },
                    {
                        "id": 4,
                        "role": "tick_label"
                    },
                    {
                        "id": 5,
                        "role": "tick_label"
                    },
                    {
                        "id": 6,
                        "role": "tick_label"
                    },
                    {
                        "id": 7,
                        "role": "tick_label"
                    },
                    {
                        "id": 8,
                        "role": "tick_label"
                    },
                    {
                        "id": 9,
                        "role": "tick_label"
                    },
                    {
                        "id": 10,
                        "role": "tick_label"
                    },
                    {
                        "id": 11,
                        "role": "tick_label"
                    },
                    {
                        "id": 12,
                        "role": "axis_title"
                    },
                    {
                        "id": 13,
                        "role": "axis_title"
                    },
                    {
                        "id": 14,
                        "role": "other"
                    }
                ]
            },
            "task4_output": {
                "_plot_bb": {
                    "height": 658,
                    "width": 659,
                    "x0": 87,
                    "y0": 10
                },
                "axes": {
                    "_x-tick-type": "markers",
                    "_x2-tick-type": null,
                    "_y-tick-type": "markers",
                    "_y2-tick-type": null,
                    "x-axis": [
                        {
                            "id": 5,
                            "tick_pt": {
                                "x": 87,
                                "y": 668
                            }
                        },
                        {
                            "id": 4,
                            "tick_pt": {
                                "x": 219,
                                "y": 668
                            }
                        },
                        {
                            "id": 3,
                            "tick_pt": {
                                "x": 351,
                                "y": 668
                            }
                        },
                        {
                            "id": 0,
                            "tick_pt": {
                                "x": 482,
                                "y": 668
                            }
                        },
                        {
                            "id": 1,
                            "tick_pt": {
                                "x": 614,
                                "y": 668
                            }
                        },
                        {
                            "id": 2,
                            "tick_pt": {
                                "x": 746,
                                "y": 668
                            }
                        }
                    ],
                    "x-axis-2": [],
                    "y-axis": [
                        {
                            "id": 11,
                            "tick_pt": {
                                "x": 87,
                                "y": 10
                            }
                        },
                        {
                            "id": 10,
                            "tick_pt": {
                                "x": 87,
                                "y": 142
                            }
                        },
                        {
                            "id": 9,
                            "tick_pt": {
                                "x": 87,
                                "y": 273
                            }
                        },
                        {
                            "id": 8,
                            "tick_pt": {
                                "x": 87,
                                "y": 405
                            }
                        },
                        {
                            "id": 7,
                            "tick_pt": {
                                "x": 87,
                                "y": 537
                            }
                        },
                        {
                            "id": 6,
                            "tick_pt": {
                                "x": 87,
                                "y": 668
                            }
                        }
                    ],
                    "y-axis-2": []
                }
            },
            "task5_output": {
                "legend_pairs": []
            }
        },
        "name": "Data Extraction",
        "output": {
            "data series": [
                {
                    "data": [
                        {
                            "x": 0.0015176579502511726,
                            "y": 0.002460846713554238
                        },
                        {
                            "x": 0.02276486925376759,
                            "y": 0.3260166183105222
                        },
                        {
                            "x": 0.025800185154269933,
                            "y": 0.16044112955902215
                        },
                        {
                            "x": 0.06981226571155394,
                            "y": 0.3731068949279213
                        },
                        {
                            "x": 0.07436523956230746,
                            "y": 0.5690632073035498
                        },
                        {
                            "x": 0.1168596621693403,
                            "y": 0.6267867721893939
                        },
                        {
                            "x": 0.18970724378139658,
                            "y": 0.6647628017195545
                        },
                        {
                            "x": 0.19122490173164775,
                            "y": 0.7543862314107335
                        },
                        {
                            "x": 0.33236709110500684,
                            "y": 0.8090717139341648
                        },
                        {
                            "x": 0.3369200649557603,
                            "y": 0.8364144551958803
                        },
                        {
                            "x": 0.38093214551304433,
                            "y": 0.8713524023636281
                        },
                        {
                            "x": 0.3854851193637978,
                            "y": 0.9062903495313758
                        },
                        {
                            "x": 0.4036970147668119,
                            "y": 0.9123665142562014
                        },
                        {
                            "x": 0.4294971999210819,
                            "y": 0.9214807613434399
                        },
                        {
                            "x": 0.47502693842861704,
                            "y": 0.9473044614239492
                        },
                        {
                            "x": 0.6207221016527296,
                            "y": 0.9624948732360133
                        },
                        {
                            "x": 0.6222397596029807,
                            "y": 0.9716091203232519
                        },
                        {
                            "x": 0.7861468182301075,
                            "y": 0.989837614497729
                        },
                        {
                            "x": 0.871135663444173,
                            "y": 0.9928756968601418
                        },
                        {
                            "x": 0.9971012733150203,
                            "y": 0.9954428764563807
                        }
                    ],
                    "name": "[unnamed data series #0]"
                },
                {
                    "data": [
                        {
                            "x": 0.010623605651758208,
                            "y": 0.007017970257173504
                        },
                        {
                            "x": 0.9986189312652715,
                            "y": 0.9989518615849675
                        }
                    ],
                    "name": "[unnamed data series #1]"
                }
            ],
            "visual elements": {
                "bars": [],
                "boxplots": [],
                "lines": [
                    [
                        {
                            "x": 88.0,
                            "y": 666.69
                        },
                        {
                            "x": 102.0,
                            "y": 453.69000000000005
                        },
                        {
                            "x": 104.0,
                            "y": 562.69
                        },
                        {
                            "x": 133.0,
                            "y": 422.69000000000005
                        },
                        {
                            "x": 136.0,
                            "y": 293.69000000000005
                        },
                        {
                            "x": 164.0,
                            "y": 255.69000000000005
                        },
                        {
                            "x": 212.0,
                            "y": 230.69000000000005
                        },
                        {
                            "x": 213.0,
                            "y": 171.69000000000005
                        },
                        {
                            "x": 306.0,
                            "y": 135.69000000000005
                        },
                        {
                            "x": 309.0,
                            "y": 117.69000000000005
                        },
                        {
                            "x": 338.0,
                            "y": 94.69000000000005
                        },
                        {
                            "x": 341.0,
                            "y": 71.69000000000005
                        },
                        {
                            "x": 353.0,
                            "y": 67.69000000000005
                        },
                        {
                            "x": 370.0,
                            "y": 61.690000000000055
                        },
                        {
                            "x": 400.0,
                            "y": 44.690000000000055
                        },
                        {
                            "x": 496.0,
                            "y": 34.690000000000055
                        },
                        {
                            "x": 497.0,
                            "y": 28.690000000000055
                        },
                        {
                            "x": 605.0,
                            "y": 16.690000000000055
                        },
                        {
                            "x": 661.0,
                            "y": 14.690000000000055
                        },
                        {
                            "x": 744.0,
                            "y": 13.0
                        }
                    ],
                    [
                        {
                            "x": 94.0,
                            "y": 663.69
                        },
                        {
                            "x": 745.0,
                            "y": 10.690000000000055
                        }
                    ]
                ],
                "scatter points": []
            }
        }
    }
}