{
    "task1": {
        "input": {},
        "name": "Chart Classification",
        "output": {
            "chart_type": "line"
        }
    },
    "task2": {
        "input": {
            "task1_output": {
                "chart_type": "line"
            }
        },
        "name": "Text Detection and Recognition",
        "output": {
            "text_blocks": [
                {
                    "id": 0,
                    "polygon": {
                        "x0": 20,
                        "x1": 47,
                        "x2": 47,
                        "x3": 20,
                        "y0": 13,
                        "y1": 13,
                        "y2": 26,
                        "y3": 26
                    },
                    "text": "0.08"
                },
                {
                    "id": 1,
                    "polygon": {
                        "x0": 20,
                        "x1": 46,
                        "x2": 46,
                        "x3": 20,
                        "y0": 89,
                        "y1": 89,
                        "y2": 102,
                        "y3": 102
                    },
                    "text": "0.04"
                },
                {
                    "id": 2,
                    "polygon": {
                        "x0": 20,
                        "x1": 46,
                        "x2": 46,
                        "x3": 20,
                        "y0": 166,
                        "y1": 166,
                        "y2": 179,
                        "y3": 179
                    },
                    "text": "0.00"
                },
                {
                    "id": 3,
                    "polygon": {
                        "x0": 13,
                        "x1": 46,
                        "x2": 46,
                        "x3": 13,
                        "y0": 244,
                        "y1": 244,
                        "y2": 255,
                        "y3": 255
                    },
                    "text": "-0.04"
                },
                {
                    "id": 4,
                    "polygon": {
                        "x0": 83,
                        "x1": 114,
                        "x2": 114,
                        "x3": 83,
                        "y0": 320,
                        "y1": 320,
                        "y2": 332,
                        "y3": 332
                    },
                    "text": "2005"
                },
                {
                    "id": 5,
                    "polygon": {
                        "x0": 153,
                        "x1": 183,
                        "x2": 183,
                        "x3": 153,
                        "y0": 320,
                        "y1": 320,
                        "y2": 332,
                        "y3": 332
                    },
                    "text": "2007"
                },
                {
                    "id": 6,
                    "polygon": {
                        "x0": 223,
                        "x1": 253,
                        "x2": 253,
                        "x3": 223,
                        "y0": 320,
                        "y1": 320,
                        "y2": 332,
                        "y3": 332
                    },
                    "text": "2009"
                },
                {
                    "id": 7,
                    "polygon": {
                        "x0": 292,
                        "x1": 321,
                        "x2": 321,
                        "x3": 292,
                        "y0": 320,
                        "y1": 320,
                        "y2": 331,
                        "y3": 331
                    },
                    "text": "2011"
                },
                {
                    "id": 8,
                    "polygon": {
                        "x0": 189,
                        "x1": 218,
                        "x2": 218,
                        "x3": 189,
                        "y0": 332,
                        "y1": 332,
                        "y2": 344,
                        "y3": 344
                    },
                    "text": "Year"
                },
                {
                    "id": 9,
                    "polygon": {
                        "x0": 0,
                        "x1": 13,
                        "x2": 13,
                        "x3": 0,
                        "y0": 64,
                        "y1": 64,
                        "y2": 253,
                        "y3": 253
                    },
                    "text": "Cumulative Average Log Growth"
                }
            ]
        }
    },
    "task3": {
        "input": {
            "task1_output": {
                "chart_type": "line"
            },
            "task2_output": {
                "text_blocks": [
                    {
                        "id": 0,
                        "polygon": {
                            "x0": 20,
                            "x1": 47,
                            "x2": 47,
                            "x3": 20,
                            "y0": 13,
                            "y1": 13,
                            "y2": 26,
                            "y3": 26
                        },
                        "text": "0.08"
                    },
                    {
                        "id": 1,
                        "polygon": {
                            "x0": 20,
                            "x1": 46,
                            "x2": 46,
                            "x3": 20,
                            "y0": 89,
                            "y1": 89,
                            "y2": 102,
                            "y3": 102
                        },
                        "text": "0.04"
                    },
                    {
                        "id": 2,
                        "polygon": {
                            "x0": 20,
                            "x1": 46,
                            "x2": 46,
                            "x3": 20,
                            "y0": 166,
                            "y1": 166,
                            "y2": 179,
                            "y3": 179
                        },
                        "text": "0.00"
                    },
                    {
                        "id": 3,
                        "polygon": {
                            "x0": 13,
                            "x1": 46,
                            "x2": 46,
                            "x3": 13,
                            "y0": 244,
                            "y1": 244,
                            "y2": 255,
                            "y3": 255
                        },
                        "text": "-0.04"
                    },
                    {
                        "id": 4,
                        "polygon": {
                            "x0": 83,
                            "x1": 114,
                            "x2": 114,
                            "x3": 83,
                            "y0": 320,
                            "y1": 320,
                            "y2": 332,
                            "y3": 332
                        },
                        "text": "2005"
                    },
                    {
                        "id": 5,
                        "polygon": {
                            "x0": 153,
                            "x1": 183,
                            "x2": 183,
                            "x3": 153,
                            "y0": 320,
                            "y1": 320,
                            "y2": 332,
                            "y3": 332
                        },
                        "text": "2007"
                    },
                    {
                        "id": 6,
                        "polygon": {
                            "x0": 223,
                            "x1": 253,
                            "x2": 253,
                            "x3": 223,
                            "y0": 320,
                            "y1": 320,
                            "y2": 332,
                            "y3": 332
                        },
                        "text": "2009"
                    },
                    {
                        "id": 7,
                        "polygon": {
                            "x0": 292,
                            "x1": 321,
                            "x2": 321,
                            "x3": 292,
                            "y0": 320,
                            "y1": 320,
                            "y2": 331,
                            "y3": 331
                        },
                        "text": "2011"
                    },
                    {
                        "id": 8,
                        "polygon": {
                            "x0": 189,
                            "x1": 218,
                            "x2": 218,
                            "x3": 189,
                            "y0": 332,
                            "y1": 332,
                            "y2": 344,
                            "y3": 344
                        },
                        "text": "Year"
                    },
                    {
                        "id": 9,
                        "polygon": {
                            "x0": 0,
                            "x1": 13,
                            "x2": 13,
                            "x3": 0,
                            "y0": 64,
                            "y1": 64,
                            "y2": 253,
                            "y3": 253
                        },
                        "text": "Cumulative Average Log Growth"
                    }
                ]
            }
        },
        "name": "Text Role Classification",
        "output": {
            "text_roles": [
                {
                    "id": 0,
                    "role": "tick_label"
                },
                {
                    "id": 1,
                    "role": "tick_label"
                },
                {
                    "id": 2,
                    "role": "tick_label"
                },
                {
                    "id": 3,
                    "role": "tick_label"
                },
                {
                    "id": 4,
                    "role": "tick_label"
                },
                {
                    "id": 5,
                    "role": "tick_label"
                },
                {
                    "id": 6,
                    "role": "tick_label"
                },
                {
                    "id": 7,
                    "role": "tick_label"
                },
                {
                    "id": 8,
                    "role": "axis_title"
                },
                {
                    "id": 9,
                    "role": "axis_title"
                }
            ]
        }
    },
    "task4": {
        "input": {
            "task1_output": {
                "chart_type": "line"
            },
            "task2_output": {
                "text_blocks": [
                    {
                        "id": 0,
                        "polygon": {
                            "x0": 20,
                            "x1": 47,
                            "x2": 47,
                            "x3": 20,
                            "y0": 13,
                            "y1": 13,
                            "y2": 26,
                            "y3": 26
                        },
                        "text": "0.08"
                    },
                    {
                        "id": 1,
                        "polygon": {
                            "x0": 20,
                            "x1": 46,
                            "x2": 46,
                            "x3": 20,
                            "y0": 89,
                            "y1": 89,
                            "y2": 102,
                            "y3": 102
                        },
                        "text": "0.04"
                    },
                    {
                        "id": 2,
                        "polygon": {
                            "x0": 20,
                            "x1": 46,
                            "x2": 46,
                            "x3": 20,
                            "y0": 166,
                            "y1": 166,
                            "y2": 179,
                            "y3": 179
                        },
                        "text": "0.00"
                    },
                    {
                        "id": 3,
                        "polygon": {
                            "x0": 13,
                            "x1": 46,
                            "x2": 46,
                            "x3": 13,
                            "y0": 244,
                            "y1": 244,
                            "y2": 255,
                            "y3": 255
                        },
                        "text": "-0.04"
                    },
                    {
                        "id": 4,
                        "polygon": {
                            "x0": 83,
                            "x1": 114,
                            "x2": 114,
                            "x3": 83,
                            "y0": 320,
                            "y1": 320,
                            "y2": 332,
                            "y3": 332
                        },
                        "text": "2005"
                    },
                    {
                        "id": 5,
                        "polygon": {
                            "x0": 153,
                            "x1": 183,
                            "x2": 183,
                            "x3": 153,
                            "y0": 320,
                            "y1": 320,
                            "y2": 332,
                            "y3": 332
                        },
                        "text": "2007"
                    },
                    {
                        "id": 6,
                        "polygon": {
                            "x0": 223,
                            "x1": 253,
                            "x2": 253,
                            "x3": 223,
                            "y0": 320,
                            "y1": 320,
                            "y2": 332,
                            "y3": 332
                        },
                        "text": "2009"
                    },
                    {
                        "id": 7,
                        "polygon": {
                            "x0": 292,
                            "x1": 321,
                            "x2": 321,
                            "x3": 292,
                            "y0": 320,
                            "y1": 320,
                            "y2": 331,
                            "y3": 331
                        },
                        "text": "2011"
                    },
                    {
                        "id": 8,
                        "polygon": {
                            "x0": 189,
                            "x1": 218,
                            "x2": 218,
                            "x3": 189,
                            "y0": 332,
                            "y1": 332,
                            "y2": 344,
                            "y3": 344
                        },
                        "text": "Year"
                    },
                    {
                        "id": 9,
                        "polygon": {
                            "x0": 0,
                            "x1": 13,
                            "x2": 13,
                            "x3": 0,
                            "y0": 64,
                            "y1": 64,
                            "y2": 253,
                            "y3": 253
                        },
                        "text": "Cumulative Average Log Growth"
                    }
                ]
            }
        },
        "name": "Axes Analysis",
        "output": {
            "_plot_bb": {
                "height": 317,
                "width": 306,
                "x0": 50,
                "y0": 0
            },
            "axes": {
                "_x-tick-type": "markers",
                "_x2-tick-type": null,
                "_y-tick-type": "markers",
                "_y2-tick-type": null,
                "x-axis": [
                    {
                        "id": 4,
                        "tick_pt": {
                            "x": 99,
                            "y": 318
                        }
                    },
                    {
                        "id": 5,
                        "tick_pt": {
                            "x": 168,
                            "y": 318
                        }
                    },
                    {
                        "id": 6,
                        "tick_pt": {
                            "x": 238,
                            "y": 318
                        }
                    },
                    {
                        "id": 7,
                        "tick_pt": {
                            "x": 308,
                            "y": 318
                        }
                    }
                ],
                "x-axis-2": [],
                "y-axis": [
                    {
                        "id": 0,
                        "tick_pt": {
                            "x": 50,
                            "y": 19
                        }
                    },
                    {
                        "id": 1,
                        "tick_pt": {
                            "x": 50,
                            "y": 96
                        }
                    },
                    {
                        "id": 2,
                        "tick_pt": {
                            "x": 50,
                            "y": 173
                        }
                    },
                    {
                        "id": 3,
                        "tick_pt": {
                            "x": 50,
                            "y": 250
                        }
                    }
                ],
                "y-axis-2": []
            }
        }
    },
    "task5": {
        "input": {
            "task1_output": {
                "chart_type": "line"
            },
            "task2_output": {
                "text_blocks": [
                    {
                        "id": 0,
                        "polygon": {
                            "x0": 20,
                            "x1": 47,
                            "x2": 47,
                            "x3": 20,
                            "y0": 13,
                            "y1": 13,
                            "y2": 26,
                            "y3": 26
                        },
                        "text": "0.08"
                    },
                    {
                        "id": 1,
                        "polygon": {
                            "x0": 20,
                            "x1": 46,
                            "x2": 46,
                            "x3": 20,
                            "y0": 89,
                            "y1": 89,
                            "y2": 102,
                            "y3": 102
                        },
                        "text": "0.04"
                    },
                    {
                        "id": 2,
                        "polygon": {
                            "x0": 20,
                            "x1": 46,
                            "x2": 46,
                            "x3": 20,
                            "y0": 166,
                            "y1": 166,
                            "y2": 179,
                            "y3": 179
                        },
                        "text": "0.00"
                    },
                    {
                        "id": 3,
                        "polygon": {
                            "x0": 13,
                            "x1": 46,
                            "x2": 46,
                            "x3": 13,
                            "y0": 244,
                            "y1": 244,
                            "y2": 255,
                            "y3": 255
                        },
                        "text": "-0.04"
                    },
                    {
                        "id": 4,
                        "polygon": {
                            "x0": 83,
                            "x1": 114,
                            "x2": 114,
                            "x3": 83,
                            "y0": 320,
                            "y1": 320,
                            "y2": 332,
                            "y3": 332
                        },
                        "text": "2005"
                    },
                    {
                        "id": 5,
                        "polygon": {
                            "x0": 153,
                            "x1": 183,
                            "x2": 183,
                            "x3": 153,
                            "y0": 320,
                            "y1": 320,
                            "y2": 332,
                            "y3": 332
                        },
                        "text": "2007"
                    },
                    {
                        "id": 6,
                        "polygon": {
                            "x0": 223,
                            "x1": 253,
                            "x2": 253,
                            "x3": 223,
                            "y0": 320,
                            "y1": 320,
                            "y2": 332,
                            "y3": 332
                        },
                        "text": "2009"
                    },
                    {
                        "id": 7,
                        "polygon": {
                            "x0": 292,
                            "x1": 321,
                            "x2": 321,
                            "x3": 292,
                            "y0": 320,
                            "y1": 320,
                            "y2": 331,
                            "y3": 331
                        },
                        "text": "2011"
                    },
                    {
                        "id": 8,
                        "polygon": {
                            "x0": 189,
                            "x1": 218,
                            "x2": 218,
                            "x3": 189,
                            "y0": 332,
                            "y1": 332,
                            "y2": 344,
                            "y3": 344
                        },
                        "text": "Year"
                    },
                    {
                        "id": 9,
                        "polygon": {
                            "x0": 0,
                            "x1": 13,
                            "x2": 13,
                            "x3": 0,
                            "y0": 64,
                            "y1": 64,
                            "y2": 253,
                            "y3": 253
                        },
                        "text": "Cumulative Average Log Growth"
                    }
                ]
            }
        },
        "name": "Legend Analysis",
        "output": {
            "legend_pairs": []
        }
    },
    "task6": {
        "input": {
            "task1_output": {
                "chart_type": "line"
            },
            "task2_output": {
                "text_blocks": [
                    {
                        "id": 0,
                        "polygon": {
                            "x0": 20,
                            "x1": 47,
                            "x2": 47,
                            "x3": 20,
                            "y0": 13,
                            "y1": 13,
                            "y2": 26,
                            "y3": 26
                        },
                        "text": "0.08"
                    },
                    {
                        "id": 1,
                        "polygon": {
                            "x0": 20,
                            "x1": 46,
                            "x2": 46,
                            "x3": 20,
                            "y0": 89,
                            "y1": 89,
                            "y2": 102,
                            "y3": 102
                        },
                        "text": "0.04"
                    },
                    {
                        "id": 2,
                        "polygon": {
                            "x0": 20,
                            "x1": 46,
                            "x2": 46,
                            "x3": 20,
                            "y0": 166,
                            "y1": 166,
                            "y2": 179,
                            "y3": 179
                        },
                        "text": "0.00"
                    },
                    {
                        "id": 3,
                        "polygon": {
                            "x0": 13,
                            "x1": 46,
                            "x2": 46,
                            "x3": 13,
                            "y0": 244,
                            "y1": 244,
                            "y2": 255,
                            "y3": 255
                        },
                        "text": "-0.04"
                    },
                    {
                        "id": 4,
                        "polygon": {
                            "x0": 83,
                            "x1": 114,
                            "x2": 114,
                            "x3": 83,
                            "y0": 320,
                            "y1": 320,
                            "y2": 332,
                            "y3": 332
                        },
                        "text": "2005"
                    },
                    {
                        "id": 5,
                        "polygon": {
                            "x0": 153,
                            "x1": 183,
                            "x2": 183,
                            "x3": 153,
                            "y0": 320,
                            "y1": 320,
                            "y2": 332,
                            "y3": 332
                        },
                        "text": "2007"
                    },
                    {
                        "id": 6,
                        "polygon": {
                            "x0": 223,
                            "x1": 253,
                            "x2": 253,
                            "x3": 223,
                            "y0": 320,
                            "y1": 320,
                            "y2": 332,
                            "y3": 332
                        },
                        "text": "2009"
                    },
                    {
                        "id": 7,
                        "polygon": {
                            "x0": 292,
                            "x1": 321,
                            "x2": 321,
                            "x3": 292,
                            "y0": 320,
                            "y1": 320,
                            "y2": 331,
                            "y3": 331
                        },
                        "text": "2011"
                    },
                    {
                        "id": 8,
                        "polygon": {
                            "x0": 189,
                            "x1": 218,
                            "x2": 218,
                            "x3": 189,
                            "y0": 332,
                            "y1": 332,
                            "y2": 344,
                            "y3": 344
                        },
                        "text": "Year"
                    },
                    {
                        "id": 9,
                        "polygon": {
                            "x0": 0,
                            "x1": 13,
                            "x2": 13,
                            "x3": 0,
                            "y0": 64,
                            "y1": 64,
                            "y2": 253,
                            "y3": 253
                        },
                        "text": "Cumulative Average Log Growth"
                    }
                ]
            },
            "task3_output": {
                "text_roles": [
                    {
                        "id": 0,
                        "role": "tick_label"
                    },
                    {
                        "id": 1,
                        "role": "tick_label"
                    },
                    {
                        "id": 2,
                        "role": "tick_label"
                    },
                    {
                        "id": 3,
                        "role": "tick_label"
                    },
                    {
                        "id": 4,
                        "role": "tick_label"
                    },
                    {
                        "id": 5,
                        "role": "tick_label"
                    },
                    {
                        "id": 6,
                        "role": "tick_label"
                    },
                    {
                        "id": 7,
                        "role": "tick_label"
                    },
                    {
                        "id": 8,
                        "role": "axis_title"
                    },
                    {
                        "id": 9,
                        "role": "axis_title"
                    }
                ]
            },
            "task4_output": {
                "_plot_bb": {
                    "height": 317,
                    "width": 306,
                    "x0": 50,
                    "y0": 0
                },
                "axes": {
                    "_x-tick-type": "markers",
                    "_x2-tick-type": null,
                    "_y-tick-type": "markers",
                    "_y2-tick-type": null,
                    "x-axis": [
                        {
                            "id": 4,
                            "tick_pt": {
                                "x": 99,
                                "y": 318
                            }
                        },
                        {
                            "id": 5,
                            "tick_pt": {
                                "x": 168,
                                "y": 318
                            }
                        },
                        {
                            "id": 6,
                            "tick_pt": {
                                "x": 238,
                                "y": 318
                            }
                        },
                        {
                            "id": 7,
                            "tick_pt": {
                                "x": 308,
                                "y": 318
                            }
                        }
                    ],
                    "x-axis-2": [],
                    "y-axis": [
                        {
                            "id": 0,
                            "tick_pt": {
                                "x": 50,
                                "y": 19
                            }
                        },
                        {
                            "id": 1,
                            "tick_pt": {
                                "x": 50,
                                "y": 96
                            }
                        },
                        {
                            "id": 2,
                            "tick_pt": {
                                "x": 50,
                                "y": 173
                            }
                        },
                        {
                            "id": 3,
                            "tick_pt": {
                                "x": 50,
                                "y": 250
                            }
                        }
                    ],
                    "y-axis-2": []
                }
            },
            "task5_output": {
                "legend_pairs": []
            }
        },
        "name": "Data Extraction",
        "output": {
            "data series": [
                {
                    "data": [
                        {
                            "x": 2003.9885057471265,
                            "y": 0.021401384083044993
                        },
                        {
                            "x": 2004.9770114942528,
                            "y": 0.04348615916955016
                        },
                        {
                            "x": 2005.9770114942528,
                            "y": 0.06590830449826988
                        },
                        {
                            "x": 2006.9770114942528,
                            "y": 0.08272491349480965
                        },
                        {
                            "x": 2007.9885057471265,
                            "y": 0.08272491349480965
                        },
                        {
                            "x": 2009.0,
                            "y": 0.006557093425605518
                        },
                        {
                            "x": 2009.9885057471265,
                            "y": -0.052404844290657386
                        },
                        {
                            "x": 2010.9885057471265,
                            "y": -0.043062283737024226
                        },
                        {
                            "x": 2012.0,
                            "y": -0.03901384083044983
                        }
                    ],
                    "name": "[unnamed data series #0]"
                },
                {
                    "data": [
                        {
                            "x": 2003.9770114942528,
                            "y": 0.020570934256055377
                        },
                        {
                            "x": 2004.9885057471265,
                            "y": 0.039333910034602064
                        },
                        {
                            "x": 2005.9885057471265,
                            "y": 0.0582266435986159
                        },
                        {
                            "x": 2007.0114942528735,
                            "y": 0.07400519031141865
                        },
                        {
                            "x": 2008.0,
                            "y": 0.0713062283737024
                        },
                        {
                            "x": 2009.0,
                            "y": -0.004887543252595168
                        },
                        {
                            "x": 2010.0229885057472,
                            "y": -0.0665484429065744
                        },
                        {
                            "x": 2011.0,
                            "y": -0.06447231833910036
                        },
                        {
                            "x": 2012.0114942528735,
                            "y": -0.06309688581314878
                        }
                    ],
                    "name": "[unnamed data series #1]"
                },
                {
                    "data": [
                        {
                            "x": 2003.9770114942528,
                            "y": 0.019117647058823534
                        },
                        {
                            "x": 2005.0344827586207,
                            "y": 0.03289792387543251
                        },
                        {
                            "x": 2005.9770114942528,
                            "y": 0.04763840830449825
                        },
                        {
                            "x": 2006.9885057471265,
                            "y": 0.05926470588235293
                        },
                        {
                            "x": 2007.9885057471265,
                            "y": 0.05511245674740483
                        },
                        {
                            "x": 2009.0,
                            "y": -0.0007352941176470701
                        },
                        {
                            "x": 2009.9885057471265,
                            "y": -0.03582179930795846
                        },
                        {
                            "x": 2011.0,
                            "y": -0.03478373702422146
                        },
                        {
                            "x": 2012.0114942528735,
                            "y": -0.03340830449826989
                        }
                    ],
                    "name": "[unnamed data series #2]"
                }
            ],
            "visual elements": {
                "bars": [],
                "boxplots": [],
                "lines": [
                    [
                        {
                            "x": 63.6,
                            "y": 132.1
                        },
                        {
                            "x": 98.0,
                            "y": 89.55000000000004
                        },
                        {
                            "x": 132.79999999999998,
                            "y": 46.35000000000002
                        },
                        {
                            "x": 167.6,
                            "y": 13.950000000000045
                        },
                        {
                            "x": 202.79999999999998,
                            "y": 13.950000000000045
                        },
                        {
                            "x": 238.0,
                            "y": 160.70000000000005
                        },
                        {
                            "x": 272.4,
                            "y": 274.2999999999999
                        },
                        {
                            "x": 307.20000000000005,
                            "y": 256.3
                        },
                        {
                            "x": 342.40000000000003,
                            "y": 248.5
                        }
                    ],
                    [
                        {
                            "x": 63.2,
                            "y": 133.7
                        },
                        {
                            "x": 98.4,
                            "y": 97.55000000000004
                        },
                        {
                            "x": 133.2,
                            "y": 61.150000000000034
                        },
                        {
                            "x": 168.79999999999998,
                            "y": 30.750000000000057
                        },
                        {
                            "x": 203.2,
                            "y": 35.950000000000045
                        },
                        {
                            "x": 238.0,
                            "y": 182.75000000000003
                        },
                        {
                            "x": 273.6,
                            "y": 301.55
                        },
                        {
                            "x": 307.6,
                            "y": 297.55
                        },
                        {
                            "x": 342.8,
                            "y": 294.9
                        }
                    ],
                    [
                        {
                            "x": 63.2,
                            "y": 136.5
                        },
                        {
                            "x": 100.0,
                            "y": 109.95000000000005
                        },
                        {
                            "x": 132.79999999999998,
                            "y": 81.55000000000004
                        },
                        {
                            "x": 168.0,
                            "y": 59.150000000000034
                        },
                        {
                            "x": 202.79999999999998,
                            "y": 67.15000000000003
                        },
                        {
                            "x": 238.0,
                            "y": 174.75000000000003
                        },
                        {
                            "x": 272.4,
                            "y": 242.34999999999997
                        },
                        {
                            "x": 307.6,
                            "y": 240.35000000000002
                        },
                        {
                            "x": 342.8,
                            "y": 237.7
                        }
                    ]
                ],
                "scatter points": []
            }
        }
    }
}